bibpy/__init__.py
bibpy/date.py
bibpy/entries.py
bibpy/error.py
bibpy/fields.py
bibpy/name.py
bibpy/parser.py
bibpy/postprocess.py
bibpy/preprocess.py
bibpy/references.py
bibpy/requirements.py
bibpy/tools.py
bibpy/doi/__init__.py
bibpy/entry/__init__.py
bibpy/entry/base.py
bibpy/entry/comment.py
bibpy/entry/entry.py
bibpy/entry/preamble.py
bibpy/entry/string.py
bibpy/lexers/__init__.py
bibpy/lexers/base_lexer.py
bibpy/lexers/biblexer.py
bibpy/lexers/name_lexer.py
bibpy/lexers/namelist_lexer.py
bibpy/scripts/__init__.py
bibpy/scripts/bibformat.py
bibpy/scripts/bibgrep.py
bibpy/scripts/bibstats.py
bibpy-1.0.1.dist-info/LICENSE
bibpy-1.0.1.dist-info/METADATA
bibpy-1.0.1.dist-info/WHEEL
bibpy-1.0.1.dist-info/entry_points.txt
bibpy-1.0.1.dist-info/top_level.txt
bibpy-1.0.1.dist-info/RECORD
