Metadata-Version: 2.1
Name: bibpy
Version: 1.0.1
Summary: Bib(la)tex parsing and useful tools
Home-page: https://bibpy.readthedocs.io/en/latest/
Author: Alexander Asp Bock
Author-email: albo.developer@gmail.com
License: BSD 3-Clause License
Project-URL: Issue Tracker, https://github.com/MisanthropicBit/bibpy/issues
Project-URL: Documentation, https://bibpy.readthedocs.io/en/latest/
Project-URL: Source, https://github.com/MisanthropicBit/bibpy
Keywords: bibpy,bibtex,biblatex,parser
Platform: All
Classifier: Development Status :: 5 - Production/Stable
Classifier: Intended Audience :: Developers
Classifier: Topic :: Utilities
Classifier: Topic :: Software Development
Classifier: License :: OSI Approved :: BSD License
Classifier: Programming Language :: Python :: 3 :: Only
Classifier: Programming Language :: Python :: 3.5
Classifier: Programming Language :: Python :: 3.6
Classifier: Programming Language :: Python :: 3.7
Classifier: Programming Language :: Python :: 3.8
Classifier: Programming Language :: Python :: Implementation :: CPython
Classifier: Programming Language :: Python :: Implementation :: PyPy
Requires-Python: >=3.5
License-File: LICENSE
Requires-Dist: funcparserlib (>=0.3.6)
